spib/__init__.py
spib/spib.py
spib/utils.py
spib-1.1.0.dist-info/AUTHORS.rst
spib-1.1.0.dist-info/LICENSE
spib-1.1.0.dist-info/METADATA
spib-1.1.0.dist-info/WHEEL
spib-1.1.0.dist-info/entry_points.txt
spib-1.1.0.dist-info/top_level.txt
spib-1.1.0.dist-info/RECORD
