Metadata-Version: 2.1
Name: spib
Version: 1.1.0
Summary: SPIB is a deep learning-based framework that learns the reaction coordinates from high dimensional molecular simulation trajectories.
Home-page: https://github.com/wangdedi1997/spib
Author: Dedi Wang
Author-email: dwang97@umd.edu
License: MIT license
Keywords: spib
Classifier: Development Status :: 2 - Pre-Alpha
Classifier: Intended Audience :: Developers
Classifier: License :: OSI Approved :: MIT License
Classifier: Natural Language :: English
Classifier: Programming Language :: Python :: 3
Classifier: Programming Language :: Python :: 3.6
Classifier: Programming Language :: Python :: 3.7
Classifier: Programming Language :: Python :: 3.8
Requires-Python: >=3.6
License-File: LICENSE
License-File: AUTHORS.rst
Requires-Dist: torch
